sagbescheid/__init__.py
sagbescheid/__main__.py
sagbescheid/argparse_ext.py
sagbescheid/notifier.py
sagbescheid/sagbescheid.py
sagbescheid/state.py
sagbescheid/state_helpers.py
sagbescheid/unit.py
sagbescheid/version.py
sagbescheid/notifiers/__init__.py
sagbescheid/notifiers/ircnotifier.py
sagbescheid/notifiers/loggingnotifier.py
sagbescheid/notifiers/mailnotifier.py
sagbescheid-0.3.0.dist-info/DESCRIPTION.rst
sagbescheid-0.3.0.dist-info/METADATA
sagbescheid-0.3.0.dist-info/RECORD
sagbescheid-0.3.0.dist-info/WHEEL
sagbescheid-0.3.0.dist-info/metadata.json
sagbescheid-0.3.0.dist-info/top_level.txt
